setup.py
pql/__init__.py
pql/aggregation.py
pql/matching.py
pql.egg-info/PKG-INFO
pql.egg-info/SOURCES.txt
pql.egg-info/dependency_links.txt
pql.egg-info/requires.txt
pql.egg-info/top_level.txt